{"dependencies":[{"name":"react"},{"name":"react-router-dom"}],"generated":{"js":"\"use strict\";\n\nObject.defineProperty(exports, \"__esModule\", {\n  value: true\n});\n\nvar _react = require(\"react\");\n\nvar _react2 = _interopRequireDefault(_react);\n\nvar _reactRouterDom = require(\"react-router-dom\");\n\nfunction _interopRequireDefault(obj) { return obj && obj.__esModule ? obj : { default: obj }; }\n\nvar AddUser = function AddUser() {\n  return _react2.default.createElement(\n    _reactRouterDom.Link,\n    { to: \"/create\" },\n    \"Create new table\"\n  );\n};\n\nexports.default = AddUser;"},"hash":"20627268af6eba0a9c0597bc490d2b96"}